airball/__init__.py
airball/analytic.py
airball/constants.py
airball/core.py
airball/environments.py
airball/imf.py
airball/stars.py
airball/tools.py
airball/units.py
airball-0.9.4.dist-info/METADATA
airball-0.9.4.dist-info/WHEEL
airball-0.9.4.dist-info/licenses/LICENSE
airball-0.9.4.dist-info/RECORD
