Metadata-Version: 2.4
Name: airball
Version: 0.9.4
Summary: A package for running and managing flybys using REBOUND.
Author-email: Garett Brown <astro@gbrown.ca>
License:                     GNU GENERAL PUBLIC LICENSE
License-File: LICENSE
Requires-Python: >=3.9
Requires-Dist: astropy
Requires-Dist: joblib
Requires-Dist: numpy
Requires-Dist: rebound>=4.4.7
Requires-Dist: scipy
